__init__.py
main.py
accidental_vulnerability-3.0.0.dist-info/METADATA
accidental_vulnerability-3.0.0.dist-info/WHEEL
accidental_vulnerability-3.0.0.dist-info/top_level.txt
accidental_vulnerability-3.0.0.dist-info/RECORD
