Metadata-Version: 2.1
Name: accidental-vulnerability
Version: 3.0.0
Summary: Accidental inherit
Author-email: Example Author <author@example.com>
Classifier: Programming Language :: Python :: 3
Classifier: License :: OSI Approved :: MIT License
Classifier: Operating System :: OS Independent
Requires-Python: >=3.8
Requires-Dist: fastapi <=0.5
Requires-Dist: safety >=3.2.4
Requires-Dist: uvicorn >=0.30.1
